snakehelp/__init__.py
snakehelp/cli.py
snakehelp/config.py
snakehelp/parameter_combinations.py
snakehelp/parameters.py
snakehelp/plotting.py
snakehelp/snakehelp.py
snakehelp/test_parameter_combinations.py
snakehelp-0.0.20.dist-info/LICENSE
snakehelp-0.0.20.dist-info/METADATA
snakehelp-0.0.20.dist-info/WHEEL
snakehelp-0.0.20.dist-info/top_level.txt
snakehelp-0.0.20.dist-info/RECORD
