Metadata-Version: 2.1
Name: snakehelp
Version: 0.0.20
Summary: Snakehelp: Making snakemake easier to use.
Home-page: https://github.com/ivargr/snakehelp
Author: Ivar Grytten
Author-email: ivar.grytten@gmail.com
License: MIT license
Keywords: snakehelp
Classifier: Development Status :: 2 - Pre-Alpha
Classifier: Intended Audience :: Developers
Classifier: License :: OSI Approved :: MIT License
Classifier: Natural Language :: English
Classifier: Programming Language :: Python :: 3.6
Requires-Python: >=3.6
License-File: LICENSE
Requires-Dist: pandas
Requires-Dist: numpy
Requires-Dist: pathos
Requires-Dist: shared-memory-wrapper
Requires-Dist: kaleido
Requires-Dist: plotly
Requires-Dist: tabulate
